py_clamav/__init__.py
py_clamav/__main__.py
py_clamav/scanner.py
py_clamav-1.0.1.dist-info/LICENSE.txt
py_clamav-1.0.1.dist-info/METADATA
py_clamav-1.0.1.dist-info/WHEEL
py_clamav-1.0.1.dist-info/top_level.txt
py_clamav-1.0.1.dist-info/RECORD
