Metadata-Version: 2.1
Name: py-clamav
Version: 1.0.1
Summary: LibClamAV ctypes binding
Home-page: https://github.com/dmitriym09/py-clamav
Author: dmitriym09
Author-email: dmitriym.09.12.1989@gmail.com
License: MIT
Keywords: antivirus,ClamAv,LibClamAV
Platform: UNKNOWN
Classifier: Development Status :: 4 - Beta
Classifier: License :: OSI Approved :: MIT License
Classifier: Programming Language :: Python :: 3
Classifier: Programming Language :: Python :: 3.8
Classifier: Operating System :: POSIX :: Linux
Requires-Python: >=3.8
